README.md
setup.py
cryptocom/__init__.py
cryptocom/api.py
cryptocom.egg-info/PKG-INFO
cryptocom.egg-info/SOURCES.txt
cryptocom.egg-info/dependency_links.txt
cryptocom.egg-info/requires.txt
cryptocom.egg-info/top_level.txt
test/test.py