Metadata-Version: 2.1
Name: cryptocom
Version: 0.3.0
Summary: Python API wrapper for crypto.com/exchange
Home-page: https://github.com/markoaurelije/crypto_com_API_python
Author: Marko
Author-email: markoaurelije@gmail.com
License: MIT
Download-URL: https://github.com/markoaurelije/crypto_com_API_python/dist/cryptocom-0.3.0.tar.gz
Platform: UNKNOWN
Classifier: License :: OSI Approved :: MIT License
Classifier: Programming Language :: Python :: 3
Classifier: Programming Language :: Python :: 3.6
